auto_download_undetected_chromedriver/README.MD
auto_download_undetected_chromedriver/__init__.py
auto_download_undetected_chromedriver/requirements.txt
auto_download_undetected_chromedriver/thirdparty.json
auto_download_undetected_chromedriver-0.16.dist-info/LICENSE.rst
auto_download_undetected_chromedriver-0.16.dist-info/METADATA
auto_download_undetected_chromedriver-0.16.dist-info/WHEEL
auto_download_undetected_chromedriver-0.16.dist-info/top_level.txt
auto_download_undetected_chromedriver-0.16.dist-info/RECORD
