Metadata-Version: 2.1
Name: auto-download-undetected-chromedriver
Version: 0.16
Summary: Script to automatically download the right undetected chromedriver version
Home-page: https://github.com/hansalemaos/auto_download_undetected_chromedriver
Author: Johannes Fischer
Author-email: aulasparticularesdealemaosp@gmail.com
License: MIT
Keywords: chromedriver,selenium,patched,bot,automation
Classifier: Development Status :: 4 - Beta
Classifier: Programming Language :: Python :: 3 :: Only
Classifier: Programming Language :: Python :: 3.10
Classifier: Topic :: Software Development :: Libraries :: Python Modules
Classifier: Topic :: Utilities
License-File: LICENSE.rst
Requires-Dist: downloadunzip
Requires-Dist: flatten-any-dict-iterable-or-whatsoever
Requires-Dist: getfilenuitkapython
Requires-Dist: list-files-with-timestats
Requires-Dist: requests
Requires-Dist: touchtouch
